__init__.py
pubpypack_harmony_mitch_chapman-0.0.2.dist-info/WHEEL
pubpypack_harmony_mitch_chapman-0.0.2.dist-info/LICENSE.txt
pubpypack_harmony_mitch_chapman-0.0.2.dist-info/RECORD
pubpypack_harmony_mitch_chapman-0.0.2.dist-info/entry_points.txt
pubpypack_harmony_mitch_chapman-0.0.2.dist-info/top_level.txt
pubpypack_harmony_mitch_chapman-0.0.2.dist-info/METADATA
imppkg/harmonic_mean.pyx
imppkg/data.json
imppkg/__init__.py
imppkg/harmonic_mean.c
imppkg/harmony.py
imppkg/harmonic_mean.cpython-39-i386-linux-gnu.so
imppkg/py.typed
