Metadata-Version: 2.1
Name: pubpypack-harmony-mitch-chapman
Version: 0.0.2
Summary: An ephemeral by-product of the exercises in 'Publishing Python Packages', by Dane Hillard
Author: Mitch Chapman
Author-email: mchapman87501@users.noreply.github.com
License: MIT License
Requires-Python: >=3.9
License-File: LICENSE.txt
Requires-Dist: termcolor<2,>=1.1.0
Provides-Extra: test
Requires-Dist: coverage[toml]; extra == "test"
Requires-Dist: pytest; extra == "test"
Requires-Dist: pytest-cov; extra == "test"
Requires-Dist: ruff; extra == "test"
